mytwitch/__init__.py
mytwitch/__main__.py
mytwitch/auth/__init__.py
mytwitch/auth/authapp.py
mytwitch/auth/user_token.py
mytwitch/exceptions.py
mytwitch/irc/__init__.py
mytwitch/irc/irc.py
mytwitch/irc/message.py
mytwitch/pubsub.py
mytwitch/request.py
mytwitch/rewards.py
mytwitch-0.11.5.dist-info/LICENSE
mytwitch-0.11.5.dist-info/WHEEL
mytwitch-0.11.5.dist-info/METADATA
mytwitch-0.11.5.dist-info/RECORD
