Metadata-Version: 2.1
Name: mytwitch
Version: 0.11.5
Summary: Twitch API interaction
Home-page: https://gitlab.com/OpenDisrupt/mytwitch
License: GPL-3.0-or-later
Author: Maximillian Strand
Author-email: maximillian.strand@protonmail.com
Requires-Python: >=3.10,<4.0
Classifier: License :: OSI Approved :: GNU General Public License v3 or later (GPLv3+)
Classifier: Programming Language :: Python :: 3
Classifier: Programming Language :: Python :: 3.10
Requires-Dist: PyYAML (>=6.0,<7.0)
Requires-Dist: lzon (>=0.1.0,<0.2.0)
Requires-Dist: websockets (>=10.0,<11.0)
Project-URL: Repository, https://gitlab.com/OpenDisrupt/mytwitch
